math_methods/__init__.py
math_methods/factorial.py
math_methods/square.py
tests/__init__.py
tests/test_factorial.py
tests/test_square.py
hlk_package-1.0.0.dist-info/METADATA
hlk_package-1.0.0.dist-info/WHEEL
hlk_package-1.0.0.dist-info/top_level.txt
hlk_package-1.0.0.dist-info/RECORD
