Metadata-Version: 2.1
Name: hlk-package
Version: 1.0.0
Summary: 何林凯的测试第三方库
Home-page: UNKNOWN
Author: helenlinken
Author-email: 1264510459@qq.com
License: UNKNOWN
Platform: UNKNOWN
Classifier: License :: OSI Approved :: MIT License
Classifier: Programming Language :: Python :: 3
Classifier: Programming Language :: Python :: 3.6
Classifier: Programming Language :: Python :: 3.7
Classifier: Programming Language :: Python :: 3.8
